LICENSE.txt
MANIFEST.in
README.txt
jsonlib2.c
setup.cfg
setup.py
jsonlib2.egg-info/PKG-INFO
jsonlib2.egg-info/SOURCES.txt
jsonlib2.egg-info/dependency_links.txt
jsonlib2.egg-info/top_level.txt
jsonlib2_simplejson/__init__.py
jsonlib2_simplejson/tests/__init__.py
jsonlib2_simplejson/tests/test_check_circular.py
jsonlib2_simplejson/tests/test_decode.py
jsonlib2_simplejson/tests/test_default.py
jsonlib2_simplejson/tests/test_dump.py
jsonlib2_simplejson/tests/test_fail.py
jsonlib2_simplejson/tests/test_float.py
jsonlib2_simplejson/tests/test_indent.py
jsonlib2_simplejson/tests/test_pass1.py
jsonlib2_simplejson/tests/test_pass2.py
jsonlib2_simplejson/tests/test_pass3.py
jsonlib2_simplejson/tests/test_separators.py
jsonlib2_simplejson/tests/test_unicode.py