Metadata-Version: 1.0
Name: jsonlib2
Version: 1.5.1
Summary: JSON serializer/deserializer for Python
Home-page: http://code.google.com/p/jsonlib2/
Author: Alec Flett
Author-email: alecf@flett.org
License: MIT
Download-URL: http://code.google.com/p/jsonlib2/downloads/list
Keywords: json
Platform: Platform Independent
Classifier: Development Status :: 5 - Production/Stable
Classifier: Intended Audience :: Developers
Classifier: License :: OSI Approved :: MIT License
Classifier: Operating System :: OS Independent
Classifier: Programming Language :: Python
Classifier: Topic :: Software Development :: Libraries :: Python Modules
